asteroid_sdk/__init__.py
asteroid_sdk/settings.py
asteroid_sdk/api/__init__.py
asteroid_sdk/api/api_logger.py
asteroid_sdk/api/asteroid_chat_supervision_manager.py
asteroid_sdk/api/supervision_runner.py
asteroid_sdk/api/generated/asteroid_api_client/__init__.py
asteroid_sdk/api/generated/asteroid_api_client/client.py
asteroid_sdk/api/generated/asteroid_api_client/errors.py
asteroid_sdk/api/generated/asteroid_api_client/py.typed
asteroid_sdk/api/generated/asteroid_api_client/types.py
asteroid_sdk/api/generated/asteroid_api_client/api/__init__.py
asteroid_sdk/api/generated/asteroid_api_client/api/api/__init__.py
asteroid_sdk/api/generated/asteroid_api_client/api/api/get_open_api.py
asteroid_sdk/api/generated/asteroid_api_client/api/api_key/__init__.py
asteroid_sdk/api/generated/asteroid_api_client/api/api_key/create_api_key.py
asteroid_sdk/api/generated/asteroid_api_client/api/api_key/get_api_keys.py
asteroid_sdk/api/generated/asteroid_api_client/api/api_key/revoke_api_key.py
asteroid_sdk/api/generated/asteroid_api_client/api/api_key/validate_api_key.py
asteroid_sdk/api/generated/asteroid_api_client/api/project/__init__.py
asteroid_sdk/api/generated/asteroid_api_client/api/project/create_project.py
asteroid_sdk/api/generated/asteroid_api_client/api/project/delete_project.py
asteroid_sdk/api/generated/asteroid_api_client/api/project/get_project.py
asteroid_sdk/api/generated/asteroid_api_client/api/project/get_projects.py
asteroid_sdk/api/generated/asteroid_api_client/api/run/__init__.py
asteroid_sdk/api/generated/asteroid_api_client/api/run/create_new_chat.py
asteroid_sdk/api/generated/asteroid_api_client/api/run/create_run.py
asteroid_sdk/api/generated/asteroid_api_client/api/run/delete_run.py
asteroid_sdk/api/generated/asteroid_api_client/api/run/get_run.py
asteroid_sdk/api/generated/asteroid_api_client/api/run/get_run_chat_count.py
asteroid_sdk/api/generated/asteroid_api_client/api/run/get_run_image_messages.py
asteroid_sdk-0.1.27.dist-info/LICENSE
asteroid_sdk-0.1.27.dist-info/METADATA
asteroid_sdk-0.1.27.dist-info/WHEEL
asteroid_sdk-0.1.27.dist-info/entry_points.txt
asteroid_sdk-0.1.27.dist-info/top_level.txt
asteroid_sdk-0.1.27.dist-info/RECORD
