Metadata-Version: 2.2
Name: asteroid_sdk
Version: 0.1.27
Summary: A Python SDK for Asteroid
Author-email: Asteroid <founders@asteroid.ai>
License: MIT License
License-File: LICENSE
Requires-Dist: requests>=2.28.0
Requires-Dist: openai>=1.0.0
Requires-Dist: anthropic>=0.3.0
Requires-Dist: litellm>=0.1.0
Requires-Dist: pydantic>=2.0.0
Requires-Dist: python-dotenv>=1.0.0
Requires-Dist: inspect-ai>=0.3.49
Requires-Dist: jinja2>=3.1.4
Requires-Dist: jsonschema>=4.19.0
Requires-Dist: pytest>=7.0
Requires-Dist: google-generativeai>=0.1.0
Requires-Dist: langfuse==2.57.12
